MANIFEST.in
README
setup.py
django_survey.egg-info/PKG-INFO
django_survey.egg-info/SOURCES.txt
django_survey.egg-info/dependency_links.txt
django_survey.egg-info/not-zip-safe
django_survey.egg-info/top_level.txt
examples/__init__.py
examples/examples.db
examples/manage.py
examples/settings.py
examples/urls.py
examples/management/__init__.py
examples/management/commands/__init__.py
examples/management/commands/selenium_test1.py
examples/site_media/survey/images/questions/2008/10/22/icon-no.gif
examples/site_media/survey/images/questions/2008/10/22/icon-unknown.gif
examples/site_media/survey/images/questions/2008/10/22/icon-yes.gif
examples/site_media/survey/images/questions/2008/10/22/icon-yes_.gif
examples/templates/base.html
examples/templates/main_page.html
survey/__init__.py
survey/admin.py
survey/forms.py
survey/models.py
survey/runtests.py
survey/tests.py
survey/urls.py
survey/views.py
survey/fixtures/testdata.json
survey/locale/en/LC_MESSAGES/django.mo
survey/locale/en/LC_MESSAGES/django.po
survey/locale/es/LC_MESSAGES/django.mo
survey/locale/es/LC_MESSAGES/django.po
survey/locale/fr/LC_MESSAGES/django.mo
survey/locale/fr/LC_MESSAGES/django.po
survey/templates/admin/survey/choice/edit_inline_tabular.html
survey/templates/admin/survey/question/edit_inline_tabular.html
survey/templates/admin/survey/survey/change_form.html
survey/templates/forms/field.html
survey/templates/forms/form.html
survey/templates/survey/answers_detail.html
survey/templates/survey/answers_list.html
survey/templates/survey/base.html
survey/templates/survey/choice_add.html
survey/templates/survey/choice_confirm_delete.html
survey/templates/survey/editable_survey_list.html
survey/templates/survey/image_confirm_delete.html
survey/templates/survey/question_add.html
survey/templates/survey/question_confirm_delete.html
survey/templates/survey/survey_add.html
survey/templates/survey/survey_confirm_delete.html
survey/templates/survey/survey_detail.html
survey/templates/survey/survey_edit.html
survey/templates/survey/survey_list.html
survey/templates/survey/thankyou.html
survey/templates/survey/includes/survey.html
survey/templates/test/survey_detail.html
