Metadata-Version: 1.0
Name: django-survey
Version: 0.0.3
Summary: A simple extensible survey application for django sites forked from http://code.google.com/p/django-survey/
Home-page: http://code.google.com/p/django-survey/
Author: Christopher Flynn, Yann Malet, Doug Napoleone
Author-email: chris@flynnguy.com
License: UNKNOWN
Platform: UNKNOWN
Classifier: Development Status :: 3 - Alpha
Classifier: Environment :: Web Environment
Classifier: Intended Audience :: Developers
Classifier: License :: OSI Approved :: BSD License
Classifier: Operating System :: OS Independent
Classifier: Programming Language :: Python
Classifier: Framework :: Django
